[
    {
        "sections": [
            {
                "title": "1. 스마트변액유니버설CI종신보험(무배당)[보장형계약]",
                "page": 1
            },
            {
                "title": "제1관보험계약의성립과유지",
                "page": 4
            },
            {
                "title": "제2관보험료의납입(계약자의주된의무)",
                "page": 9
            },
            {
                "title": "제3관보험금의지급(회사의주된의무)",
                "page": 14
            },
            {
                "title": "제4관특별계정에관한사항",
                "page": 17
            },
            {
                "title": "제5관보험계약시계약자의계약전알릴의무등",
                "page": 20
            },
            {
                "title": "제6관보험금지급등의절차",
                "page": 21
            },
            {
                "title": "제7관분쟁조정등",
                "page": 24
            },
            {
                "title": "별표1",
                "page": 26
            },
            {
                "title": "별표2",
                "page": 27
            },
            {
                "title": "별표3",
                "page": 28
            },
            {
                "title": "별표4",
                "page": 39
            },
            {
                "title": "별표5",
                "page": 42
            },
            {
                "title": "별표6",
                "page": 43
            },
            {
                "title": "2. 스마트변액유니버설CI종신보험(무배당)[적립형계약]",
                "page": 44
            },
            {
                "title": "제1관보험계약의성립과유지",
                "page": 46
            },
            {
                "title": "제2관보험료의납입(계약자의주된의무)",
                "page": 49
            },
            {
                "title": "제3관보험금의지급(회사의주된의무)",
                "page": 50
            },
            {
                "title": "제4관특별계정에관한사항",
                "page": 51
            },
            {
                "title": "제5관기타사항",
                "page": 54
            },
            {
                "title": "적립형계약의보험금지급기준표",
                "page": 55
            },
            {
                "title": "3. CI두번보장특약(갱신형,무배당)",
                "page": 56
            },
            {
                "title": "4. 뉴CI보장특약(갱신형,무배당)",
                "page": 69
            },
            {
                "title": "5. 리빙케어보장특약(갱신형,무배당)[최대80세갱신형]",
                "page": 78
            },
            {
                "title": "6. 리빙케어보장특약(갱신형,무배당)[최대100세갱신형]",
                "page": 92
            },
            {
                "title": "7. 정기특약(무배당)",
                "page": 105
            },
            {
                "title": "8. 체감정기특약(무배당)",
                "page": 112
            },
            {
                "title": "9. 체증정기특약(무배당)",
                "page": 120
            },
            {
                "title": "10. 가족생활자금특약(무배당)",
                "page": 128
            },
            {
                "title": "11. 재해사망특약(무배당)",
                "page": 136
            },
            {
                "title": "12. 고도장해보장특약(무배당)",
                "page": 143
            },
            {
                "title": "13. 재해장해특약(무배당)",
                "page": 150
            },
            {
                "title": "14. 기초응급자금특약(무배당)",
                "page": 158
            },
            {
                "title": "15. 재해치료비보장특약(갱신형,무배당)",
                "page": 167
            },
            {
                "title": "16. 실버케어보장특약(무배당)",
                "page": 176
            },
            {
                "title": "17. 암치료비특약(갱신형,무배당)",
                "page": 185
            },
            {
                "title": "18. 특정질병수술보장특약(갱신형,무배당)",
                "page": 197
            },
            {
                "title": "19. 신입원특약(갱신형,무배당)",
                "page": 212
            },
            {
                "title": "20. 입원특약(갱신형,무배당)",
                "page": 221
            },
            {
                "title": "21. 특정질병입원특약(갱신형,무배당)",
                "page": 230
            },
            {
                "title": "22. 실손의료비보장특약(갱신형,무배당)",
                "page": 246
            },
            {
                "title": "23. 건강우대특약(무배당)",
                "page": 272
            },
            {
                "title": "24. 특별조건부특약",
                "page": 274
            },
            {
                "title": "25. 특정부위·질병부담보특약",
                "page": 276
            },
            {
                "title": "26. 선지급서비스특약",
                "page": 280
            },
            {
                "title": "27. 사후정리특약",
                "page": 284
            },
            {
                "title": "28. 지정대리청구서비스특약",
                "page": 286
            },
            {
                "title": "29. 계약승계특약",
                "page": 288
            },
            {
                "title": "30. 유가족연금전환특약(무배당)",
                "page": 290
            },
            {
                "title": "31. 플러스연금전환특약(무배당)",
                "page": 294
            }
        ],
        "start_date": "180721",
        "name": "스마트변액유니버설CI종신보험(무배당)"
    }
]